citerm/__init__.py
citerm/__main__.py
citerm/citerm.tcss
citerm-0.0.9.dist-info/METADATA
citerm-0.0.9.dist-info/WHEEL
citerm-0.0.9.dist-info/entry_points.txt
citerm-0.0.9.dist-info/licenses/LICENSE
citerm-0.0.9.dist-info/RECORD
