Metadata-Version: 2.1
Name: citerm
Version: 0.0.9
Summary: A tool to watch CI logs in the terminal
Project-URL: Homepage, https://github.com/superlevure/citerm
Project-URL: Bug Tracker, https://github.com/superlevure/citerm/issues
Author-email: superlevure <superlevure.dev@gmail.com>
License-File: LICENSE
Classifier: License :: OSI Approved :: MIT License
Classifier: Operating System :: OS Independent
Classifier: Programming Language :: Python :: 3
Requires-Python: >=3.10
Requires-Dist: python-gitlab~=3.15
Requires-Dist: textual~=0.39
Provides-Extra: dev
Requires-Dist: textual-dev==1.2.1; extra == 'dev'
